playlist_kreator/__init__.py
playlist_kreator/cli.py
playlist_kreator/common.py
playlist_kreator/providers/__init__.py
playlist_kreator/providers/gmusic.py
playlist_kreator/providers/spotify.py
playlist_kreator-0.0.3.data/scripts/playlist-kreator
playlist_kreator-0.0.3.dist-info/METADATA
playlist_kreator-0.0.3.dist-info/RECORD
playlist_kreator-0.0.3.dist-info/WHEEL
playlist_kreator-0.0.3.dist-info/top_level.txt
