Metadata-Version: 2.1
Name: playlist-kreator
Version: 0.0.3
Summary: Create playlists easily from a list of artists, using their top songs.
Home-page: https://github.com/epayet/playlist_kreator
Author: Emmanuel Payet
Author-email: contact@emmanuel-payet.me
License: MIT
Keywords: music googlemusic playlist
Platform: UNKNOWN
Classifier: Development Status :: 3 - Alpha
Classifier: Intended Audience :: End Users/Desktop
Classifier: Topic :: Internet
Classifier: License :: OSI Approved :: MIT License
Classifier: Programming Language :: Python :: 3
Classifier: Programming Language :: Python :: 3.3
Classifier: Programming Language :: Python :: 3.4
Classifier: Programming Language :: Python :: 3.5
Classifier: Programming Language :: Python :: 3.6
Requires-Dist: appdirs (==1.4.3)
Requires-Dist: beautifulsoup4 (==4.6.0)
Requires-Dist: certifi (==2018.4.16)
Requires-Dist: chardet (==3.0.4)
Requires-Dist: click (==6.7)
Requires-Dist: decorator (==4.3.0)
Requires-Dist: first (==2.0.1)
Requires-Dist: furl (==1.2)
Requires-Dist: future (==0.16.0)
Requires-Dist: gmusicapi (==11.0.1)
Requires-Dist: gpsoauth (==0.4.1)
Requires-Dist: httplib2 (==0.11.3)
Requires-Dist: idna (==2.7)
Requires-Dist: lxml (==4.2.3)
Requires-Dist: mechanicalsoup (==0.10.0)
Requires-Dist: mock (==2.0.0)
Requires-Dist: mutagen (==1.41.0)
Requires-Dist: oauth2client (==4.1.2)
Requires-Dist: orderedmultidict (==1.0)
Requires-Dist: pbr (==4.2.0)
Requires-Dist: pip-tools (==2.0.2)
Requires-Dist: proboscis (==1.2.6.0)
Requires-Dist: protobuf (==3.6.0)
Requires-Dist: pyasn1-modules (==0.2.2)
Requires-Dist: pyasn1 (==0.4.4)
Requires-Dist: pycryptodomex (==3.6.4)
Requires-Dist: python-dateutil (==2.7.3)
Requires-Dist: requests (==2.19.1)
Requires-Dist: rsa (==3.4.2)
Requires-Dist: six (==1.11.0)
Requires-Dist: spotipy (==2.4.4)
Requires-Dist: urllib3 (==1.23)
Requires-Dist: validictory (==1.1.2)
